{
  "users": [
    {
      "id": 1,
      "name": "Myra"
    },
    {
      "name": "Natalie Jenkins Sr.",
      "id": 2
    },
    {
      "name": "Kenneth Schmidt",
      "id": 3
    },
    {
      "name": "Andres Davis",
      "id": 4
    },
    {
      "name": "Franklin Watsica",
      "id": 5
    },
    {
      "name": "Amelia Mante",
      "id": 6
    },
    {
      "name": "Mandy Hagenes",
      "id": 7
    },
    {
      "name": "Ms. Bessie Mraz",
      "id": 8
    },
    {
      "name": "Mr. Monique Streich",
      "id": 9
    },
    {
      "name": "Mr. Tamara Hessel",
      "id": 10
    },
    {
      "name": "Dewey McClure",
      "id": 11
    },
    {
      "name": "Anita Heaney",
      "id": 12
    },
    {
      "name": "Christian Bode",
      "id": 13
    },
    {
      "name": "Monique Harris",
      "id": 14
    },
    {
      "name": "Dallas Jacobi",
      "id": 15
    },
    {
      "name": "Ivan Batz",
      "id": 16
    },
    {
      "name": "Rick Cummerata",
      "id": 17
    },
    {
      "name": "Tom Romaguera",
      "id": 18
    },
    {
      "name": "Elbert Kertzmann",
      "id": 19
    },
    {
      "name": "Johnathan Williamson",
      "id": 20
    },
    {
      "name": "Everett Homenick",
      "id": 21
    },
    {
      "name": "Luke Stokes",
      "id": 22
    },
    {
      "name": "Angela Gutkowski",
      "id": 23
    },
    {
      "name": "Rebecca Bradtke MD",
      "id": 24
    },
    {
      "name": "Dolores Mertz",
      "id": 25
    },
    {
      "name": "Jessie Wehner",
      "id": 26
    },
    {
      "name": "Shari Cummerata",
      "id": 27
    }
  ],
  "albums": [],
  "photos": []
}